juntagrico/__init__.py
juntagrico/admin.py
juntagrico/apps.py
juntagrico/checks.py
juntagrico/config.py
juntagrico/context_processors.py
juntagrico/forms.py
juntagrico/models.py
juntagrico/signals.py
juntagrico/urls.py
juntagrico/view_decorators.py
juntagrico/views_admin.py
juntagrico/views_create_subscription.py
juntagrico/views_iso20022.py
juntagrico/views_subscription.py
juntagrico/admins/__init__.py
juntagrico/admins/admin_decorators.py
juntagrico/admins/area_admin.py
juntagrico/admins/assignment_admin.py
juntagrico/admins/billing_period_admin.py
juntagrico/admins/delivery_admin.py
juntagrico/admins/depot_admin.py
juntagrico/admins/filters.py
juntagrico/admins/job_admin.py
juntagrico/admins/job_type_admin.py
juntagrico/admins/list_message_admin.py
juntagrico/admins/location_admin.py
juntagrico/admins/member_admin.py
juntagrico/admins/one_time_job_admin.py
juntagrico/admins/share_admin.py
juntagrico/admins/subscription_admin.py
juntagrico/admins/subscription_product_admin.py
juntagrico/admins/subscription_size_admin.py
juntagrico/admins/subscription_type_admin.py
juntagrico/admins/tour_admin.py
juntagrico/admins/forms/__init__.py
juntagrico/admins/forms/admin_edit_share_dates.py
juntagrico/admins/forms/delivery_copy_form.py
juntagrico/admins/forms/import_export_form.py
juntagrico/admins/forms/job_copy_form.py
juntagrico/admins/forms/location_replace_form.py
juntagrico/admins/forms/subscription_admin_form.py
juntagrico/admins/inlines/__init__.py
juntagrico/admins/inlines/assignment_inline.py
juntagrico/admins/inlines/contact_inline.py
juntagrico/admins/inlines/delivery_inline.py
juntagrico/admins/inlines/depot_subscriptiontype_inline.py
juntagrico/admins/inlines/extra_subscription_inline.py
juntagrico/admins/inlines/job_extra_inline.py
juntagrico/admins/inlines/subscription_membership_inlines.py
juntagrico/admins/inlines/subscription_part_inlines.py
juntagrico/dao/__init__.py
juntagrico/dao/activityareadao.py
juntagrico/dao/assignmentdao.py
juntagrico-1.7.9.dist-info/licenses/LICENCE.txt
juntagrico-1.7.9.dist-info/METADATA
juntagrico-1.7.9.dist-info/WHEEL
juntagrico-1.7.9.dist-info/top_level.txt
juntagrico-1.7.9.dist-info/RECORD
