Metadata-Version: 2.4
Name: juntagrico
Version: 1.7.9
Summary: juntagrico is a management platform for community gardens and vegetable cooperatives.
Author-email: juntagrico <python@juntagrico.org>
Project-URL: Homepage, https://www.juntagrico.org
Project-URL: Issues, https://github.com/juntagrico/juntagrico/issues
Project-URL: Documentation, https://juntagrico.readthedocs.io
Classifier: Development Status :: 5 - Production/Stable
Classifier: Environment :: Web Environment
Classifier: Framework :: Django
Classifier: Framework :: Django :: 4.2
Classifier: Intended Audience :: Developers
Classifier: Intended Audience :: Other Audience
Classifier: License :: OSI Approved :: GNU Lesser General Public License v3 (LGPLv3)
Classifier: Operating System :: OS Independent
Classifier: Programming Language :: Python
Classifier: Programming Language :: Python :: 3.9
Classifier: Programming Language :: Python :: 3.10
Classifier: Programming Language :: Python :: 3.11
Classifier: Topic :: Internet :: WWW/HTTP :: Site Management
Requires-Python: >=3.9
License-File: LICENCE.txt
Requires-Dist: Django~=4.2.22
Requires-Dist: django-admin-sortable2~=2.3.0
Requires-Dist: django-crispy-forms~=1.14.0
Requires-Dist: django-impersonate~=1.9.1
Requires-Dist: django-polymorphic~=3.1.0
Requires-Dist: django-richtextfield~=1.6.1
Requires-Dist: django-import-export~=4.2.0
Requires-Dist: icalendar~=5.0.0
Requires-Dist: schwifty==2023.6.0
Requires-Dist: xhtml2pdf==0.2.17
Requires-Dist: svglib<1.6.0
Requires-Dist: XlsxWriter==3.1.4
Requires-Dist: python-dateutil~=2.8.2
Requires-Dist: fontawesomefree~=6.4.2
Dynamic: license-file
